pydt_range/__init__.py
pydt_range/datetime_range.py
pydt_range-1.1.0.dist-info/WHEEL
pydt_range-1.1.0.dist-info/METADATA
pydt_range-1.1.0.dist-info/RECORD
