Metadata-Version: 2.1
Name: pydt-range
Version: 1.1.0
Summary: pydt-range is purely python mini library that allows to iterate over datetime objects with a specified step (similar to built-in range())
Home-page: https://github.com/skroll182/pydt-range
Author: Kirill Olar
Author-email: kirill.olar26@gmail.com
Requires-Python: >=3.7,<4.0
Classifier: Programming Language :: Python :: 3
Classifier: Programming Language :: Python :: 3.10
Classifier: Programming Language :: Python :: 3.7
Classifier: Programming Language :: Python :: 3.8
Classifier: Programming Language :: Python :: 3.9
Requires-Dist: python-dateutil (>=2.8.2,<3.0.0)
Project-URL: Repository, https://github.com/skroll182/pydt-range
